sparse_profile/__init__.py
sparse_profile/sparse_profile.py
sparse_profile-0.1.1.dist-info/LICENSE
sparse_profile-0.1.1.dist-info/METADATA
sparse_profile-0.1.1.dist-info/WHEEL
sparse_profile-0.1.1.dist-info/top_level.txt
sparse_profile-0.1.1.dist-info/RECORD
