Metadata-Version: 2.1
Name: sparse-profile
Version: 0.1.1
Summary: EDA on sparse data for classification problems
Home-page: https://github.com/domarp/sparse_profile
Author: Pramod Balakrishnan
Author-email: prmdbk@gmail.com
License: MIT
Download-URL: https://github.com/domarp/sparse_profile/archive/refs/tags/v0.1.1.tar.gz
Keywords: eda,sparse data,classification
Platform: UNKNOWN
Classifier: Development Status :: 3 - Alpha
Classifier: Intended Audience :: Developers
Classifier: Topic :: Software Development :: Build Tools
Classifier: License :: OSI Approved :: MIT License
Classifier: Programming Language :: Python :: 3
Classifier: Programming Language :: Python :: 3.4
Classifier: Programming Language :: Python :: 3.5
Classifier: Programming Language :: Python :: 3.6
Classifier: Programming Language :: Python :: 3.7
Classifier: Programming Language :: Python :: 3.8
Classifier: Programming Language :: Python :: 3.9
Requires-Dist: pandas
Requires-Dist: numpy
